{"frequency_mhz":100,"implementation_status":"PASS","route_complete":true,"wns_ns":1.404,"tns_ns":0.0,"whs_ns":0.019,"ths_ns":0.0,"resources":{"lut":23649,"ff":9721,"lutram":812,"bram18":8,"bram36":1,"bram_tiles":5,"dsp48e2":12,"uram":0},"top":"mini_loihi_v9_0c_image_top","production_image_physically_validated":true,"production_image_neuron_count":2,"production_image_neuron_width":8,"balanced_profile_physically_validated":false,"balanced_profile_reason":"The frozen checked-in production image top does not instantiate the 256/1024 capacity profile."}
